[
    {
        "tipo": "temperatura",
        "identificador": "T5",
        "valor": "30"
    },
    {
        "tipo": "temperatura",
        "identificador": "T5",
        "valor": "30"
    },
    {
        "tipo": "temperatura",
        "identificador": "T5",
        "valor": "30"
    },
    {
        "tipo": "temperatura",
        "identificador": "T5",
        "valor": "30"
    },
    {
        "tipo": "temperatura",
        "identificador": "T5",
        "valor": "30"
    },
    {
        "tipo": "temperatura",
        "identificador": "T5",
        "valor": "30"
    }
]